saltlab/__init__.py
saltlab/bootstrap-salt.sh
saltlab/cli.py
saltlab/client.py
saltlab/cluster.py
saltlab/desert.py
saltlab/di.py
saltlab-0.1.0.dist-info/entry_points.txt
saltlab-0.1.0.dist-info/WHEEL
saltlab-0.1.0.dist-info/METADATA
saltlab-0.1.0.dist-info/RECORD
